FQCS/__init__.py
FQCS/detector.py
FQCS/fqcs_api.py
FQCS/fqcs_constants.py
FQCS/helper.py
FQCS/manager.py
FQCS/tf2_yolov4/__init__.py
FQCS/tf2_yolov4/anchors.py
FQCS/tf2_yolov4/convert_darknet_weights.py
FQCS/tf2_yolov4/csp_darknet53.py
FQCS/tf2_yolov4/download.py
FQCS/tf2_yolov4/layers.py
FQCS/tf2_yolov4/model.py
FQCS/tf2_yolov4/weights.py
FQCS/tf2_yolov4/yolov3_head.py
FQCS/tf2_yolov4/yolov4_neck.py
FQCS-1.2.5.dist-info/LICENSE
FQCS-1.2.5.dist-info/METADATA
FQCS-1.2.5.dist-info/WHEEL
FQCS-1.2.5.dist-info/top_level.txt
FQCS-1.2.5.dist-info/RECORD
