Metadata-Version: 2.1
Name: FQCS
Version: 1.2.5
Summary: This is for FQCS Capstone Project
Home-page: https://github.com/trannamtrung1st/FQCS-Research
Author: FQCS Team
Author-email: trannamtrung1st@gmail.com
License: UNKNOWN
Platform: UNKNOWN
Classifier: Programming Language :: Python :: 3
Classifier: License :: OSI Approved :: MIT License
Classifier: Operating System :: OS Independent
Requires-Python: >=3.5
Requires-Dist: numpy
Requires-Dist: imutils
Requires-Dist: opencv-python
Requires-Dist: scipy
Requires-Dist: tensorflow
Requires-Dist: tensorflow-addons
Requires-Dist: trio
